django_datatable_builder/__init__.py
django_datatable_builder/datatable_builder.py
django_datatable_builder/static/DataTable-css/bootstrap.css
django_datatable_builder/static/DataTable-css/bootstrap.css.map
django_datatable_builder/static/DataTable-css/datatables-con.css
django_datatable_builder/static/DataTable-css/datatables-con.css.map
django_datatable_builder/static/DataTable-css/datatables-sin.css
django_datatable_builder/static/DataTable-css/datatables-sin.css.map
django_datatable_builder/static/DataTable-scss/bootstrap.scss
django_datatable_builder/static/DataTable-scss/datatables-con.scss
django_datatable_builder/static/DataTable-scss/datatables-sin.scss
django_datatable_builder/static/DataTable-scss/.sass-cache/26896bd411bdec25e8f7a17a6add78e1508bab36/datatables-con.scssc
django_datatable_builder/static/DataTable-scss/.sass-cache/26896bd411bdec25e8f7a17a6add78e1508bab36/datatables-sin.scssc
django_datatable_builder/static/DataTables-con/datatables.css
django_datatable_builder/static/DataTables-con/datatables.js
django_datatable_builder/static/DataTables-con/datatables.min.css
django_datatable_builder/static/DataTables-con/datatables.min.js
django_datatable_builder/static/DataTables-con-bulma/datatables.css
django_datatable_builder/static/DataTables-con-bulma/datatables.js
django_datatable_builder/static/DataTables-con-bulma/datatables.min.css
django_datatable_builder/static/DataTables-con-bulma/datatables.min.js
django_datatable_builder/static/DataTables-sin/datatables.css
django_datatable_builder/static/DataTables-sin/datatables.js
django_datatable_builder/static/DataTables-sin/datatables.min.css
django_datatable_builder/static/DataTables-sin/datatables.min.js
django_datatable_builder/static/DataTables-sin-bulma/datatables.css
django_datatable_builder/static/DataTables-sin-bulma/datatables.js
django_datatable_builder/static/DataTables-sin-bulma/datatables.min.css
django_datatable_builder/static/DataTables-sin-bulma/datatables.min.js
django_datatable_builder-2.0.0.dist-info/licenses/LICENSE
django_datatable_builder-2.0.0.dist-info/METADATA
django_datatable_builder-2.0.0.dist-info/WHEEL
django_datatable_builder-2.0.0.dist-info/top_level.txt
django_datatable_builder-2.0.0.dist-info/RECORD
