Metadata-Version: 2.4
Name: django-datatable-builder
Version: 2.0.0
Summary: Componente reutilizable para generar datatables en Django con soporte para htmx y Bootstrap
Author-email: Mateo <mateodemartino@email.com>
Project-URL: Homepage, https://github.com/MateoDeMartino/django-datatable-builder
Classifier: Framework :: Django
Classifier: Programming Language :: Python :: 3
Classifier: License :: OSI Approved :: MIT License
Classifier: Operating System :: OS Independent
Requires-Python: >=3.10
License-File: LICENSE
Requires-Dist: django>=5.0
Dynamic: license-file
